segment_tree/__init__.py
segment_tree/multidimensional_segment_tree.py
segment_tree/operations.py
segment_tree/segment_tree.py
segment_tree-0.3.2.dist-info/DESCRIPTION.rst
segment_tree-0.3.2.dist-info/METADATA
segment_tree-0.3.2.dist-info/RECORD
segment_tree-0.3.2.dist-info/WHEEL
segment_tree-0.3.2.dist-info/metadata.json
segment_tree-0.3.2.dist-info/top_level.txt
