Metadata-Version: 2.0
Name: segment-tree
Version: 0.3.2
Summary: Multidimensional segment tree with ranges updates.
Home-page: https://github.com/evgeth/segment_tree
Author: Evgeny Yurtaev
Author-email: eugene@yurtaev.com
License: MIT
Keywords: segment,tree,range,rmq,multidimensional
Platform: UNKNOWN
Requires-Python: >=3
